{
"DASHBOARD_LITERAL": "Dashboard",
  "BALANCE_LITERAL": "Balance",
  "STATUS_LITERAL": "Status",

  "AKTIV": "Aktiv",
  "PENDING": "An der Maach",
  "INAKTIV": "Inaktiv",
  "GEFROREN": "Gefruer / festgeschriwwen",
  "ABGESAGT": "Ofgebrach",
  "RUNNING": "Leeft",

  "ACCEPT_LITERAL": "Akzeptéieren",
  "REJECT_LITERAL": "Ofleenen",
  "CANCEL_LITERAL": "Ofbriechen",
  "REACTIVATE_LITERAL": "Reaktivéieren",
  "FREEZE_LITERAL": "Afréieren",
  "UNFREEZE_LITERAL": "Entdeeën",

  "SETTINGS_LITERAL": "Astellungen",
  "USERNAME_LITERAL": "Benotzernumm",
  "PASSWORD_LITERAL": "Passwuert",
  "EMAIL_LITERAL": "Email",
  "DISPLAY_NAME_LITERAL": "Numm uweisen"
  "USER_DATA_LITERAL": "Notzerdaten",
 
 "CURRENCY_LITERAL": "Währung",
  "PREFERRED_PAYMENT_TARGET_LITERAL": "Preferéiert Zuelungszil",
  "CLEARING_FLEXIBILITY_LITERAL": "Ausgläichsflexibilitéit",
  "ENTER_USERNAME_EMAIL": "Benotzernumm aginn, E-Mail ...",
  "USER_NOT_FOUND_LITERAL": "Benotzer net fonnt",
  "USER_FOUND_LITERAL": "Benotzer fonnt!",
  "SEARCHING_LITERAL": "Sichen /op der Sich ...",

  "SIGNIN_LITERAL": "Aloggen",
  "LOGOUT_LITERAL": "Ausloggen",
  "SIGNUP_LITERAL": "Umellen",
  "ALREADY_HAVE_AN_ACCOUNT_LITERAL": "Schonn ee Konto hunn",

  "CONNECTIONS_LITERAL": "Verbindungen",
  "CONNECTION_TO": "Verbindung zu",
  "CONNECTIONS_LOADING_ERROR": "Feeler beim Luede vun de Verbindungen",
  "NO_CONNECTIONS": "Dir hutt nach keng Verbindungen.",
  "CONNECTION_STATUS": "Verbindungsstatus",
  "CONNECTION_REQUEST_SENT": "Verbindungsufro geschéckt.",
  "ACCEPTING_CONNECTION_LITERAL": "Verbindung akzeptéieren",
  "REJECTING_CONNECTION_LITERAL": "Verbindung ofleenen",
  "CANCELING_CONNECTION_LITERAL": "Verbindung annuléieren",
  "REACTIVATING_CONNECTION_LITERAL": "Verbindung reaktivéieren",
  "CONNECTION_ALREADY_EXISTS_LITERAL": "Verbindung besteet schonns",
  "WHOM_SEND_CONNECTION": "U wien wëllt Dir eng Verbindung schécken?",
  "CONFIRM_CONNECTION_LITERAL": "Verbindung bestätegen",
  
  "CREDIT_LINE_LITERAL": "Kreditlinn",
  "CREDIT_LINES_LITERAL": "Kreditlinnen",
  "CREDIT_LINES_LOADING_ERROR": "Feeler beim Luede vun de Kreditlinnen",
  "NO_CREDIT_LINES_LITERAL": "Keng Kreditlinnen",
  "NO_CREDIT_LINES": "Dir hutt nach keng Kredidtlinnen.",
  "CREDIT_LINE_STATUS": "Status vun de Kreditlinnen",
  "ONE_TIME_FEE_LABEL": "Fraisen",
  "INTEREST_RATE_LABEL": "Zënssaz",

  "FOR_CONVERSION_LITERAL": "Ze Konvertéieren",
  "NO_CONVERSION_LABEL": "Konvertéierung net aktivéiert / fräiginn/erlaabt",
  "GRANTED_LITERAL": "Accordéiert",
  
  "IOUS_LITERAL": "IOUs / Meng Scholden",
  "NO_IOUS_LITERAL": "Keng IOUs / Keng Scholden",
  "NEXT_SETTLEMENTS_LITERAL": "Nächst Kontos-Berengegungen",
  
  "SETTINGS_LOADING_ERROR": "Feeler beim Luede vun den Astellungen",
  "APP_LANGUAGE_LITERAL": "App-Sprooch",
  
  "RETRY_LITERAL": "nach enker probéieren",
  "FAILURE_VIEW_TITLE": "Eppes ass schief gaangen.",
  "FAILURE_VIEW_LABEL": "Verstanen",
  "FAILURE_VIEW_HELPER": "Probéiert wannechgelift an e puer Minutten nach enker.",

  "RECEIVER_LITERAL": "Empfänger",
  "FROM_LITERAL": "vun",
  "TO_LITERAL": "un",
  "USED_LITERAL": "benotzt",
  "AVAILABLE_LITERAL": "Verfügbar",
  "UP_TO_LITERAL": "Bis zu",
  "ENTER_LITERAL": "Enter",
  "NEXT_LITERAL": "Weider",
  "CONFIRM_LITERAL": "Bestätegen",
  "DAYS_LITERAL": "Deeg",
  "EMPTY_LITERAL": "Eidel",

  "REVIEW_BEFORE_CONFIRMATION_LITERAL": "Virun der Bestätegung iwwerpréiwen",
  "PROCESSING_YOUR_REQUEST_LITERAL": "Är Ufro gëtt beaarbecht"
}
